odoo/addons/stock_intercompany/README.rst
odoo/addons/stock_intercompany/__init__.py
odoo/addons/stock_intercompany/__manifest__.py
odoo/addons/stock_intercompany/i18n/es.po
odoo/addons/stock_intercompany/i18n/it.po
odoo/addons/stock_intercompany/i18n/stock_intercompany.pot
odoo/addons/stock_intercompany/models/__init__.py
odoo/addons/stock_intercompany/models/res_company.py
odoo/addons/stock_intercompany/models/res_config_settings.py
odoo/addons/stock_intercompany/models/stock_picking.py
odoo/addons/stock_intercompany/readme/CONFIGURE.rst
odoo/addons/stock_intercompany/readme/CONTRIBUTORS.rst
odoo/addons/stock_intercompany/readme/DESCRIPTION.rst
odoo/addons/stock_intercompany/static/description/icon.png
odoo/addons/stock_intercompany/static/description/index.html
odoo/addons/stock_intercompany/tests/__init__.py
odoo/addons/stock_intercompany/tests/test_intercompany_picking.py
odoo/addons/stock_intercompany/views/res_config_settings.xml
odoo14_addon_stock_intercompany-14.0.1.1.2.dev12.dist-info/METADATA
odoo14_addon_stock_intercompany-14.0.1.1.2.dev12.dist-info/WHEEL
odoo14_addon_stock_intercompany-14.0.1.1.2.dev12.dist-info/top_level.txt
odoo14_addon_stock_intercompany-14.0.1.1.2.dev12.dist-info/RECORD
